{
  "font-families": {
    "labels": {
      "value": "FreightSans Pro",
      "type": "fontFamilies"
    },
    "body": {
      "value": "Charter ITC Std",
      "type": "fontFamilies"
    },
    "titles": {
      "value": "Simplon Mono",
      "type": "fontFamilies"
    },
    "headlines": {
      "value": "United Sans Cond",
      "type": "fontFamilies"
    },
    "buttons": {
      "value": "FreightSans Pro",
      "type": "fontFamilies"
    }
  },
  "palette": {
    "brand": {
      "primary": {
        "value": "#1c6a65",
        "type": "color"
      }
    }
  }
}